mailtrap/__init__.py
mailtrap/client.py
mailtrap/config.py
mailtrap/exceptions.py
mailtrap/http.py
mailtrap/api/__init__.py
mailtrap/api/contacts.py
mailtrap/api/general.py
mailtrap/api/sending.py
mailtrap/api/suppressions.py
mailtrap/api/templates.py
mailtrap/api/testing.py
mailtrap/api/resources/__init__.py
mailtrap/api/resources/account_accesses.py
mailtrap/api/resources/accounts.py
mailtrap/api/resources/attachments.py
mailtrap/api/resources/billing.py
mailtrap/api/resources/contact_events.py
mailtrap/api/resources/contact_exports.py
mailtrap/api/resources/contact_fields.py
mailtrap/api/resources/contact_imports.py
mailtrap/api/resources/contact_lists.py
mailtrap/api/resources/contacts.py
mailtrap/api/resources/inboxes.py
mailtrap/api/resources/messages.py
mailtrap/api/resources/permissions.py
mailtrap/api/resources/projects.py
mailtrap/api/resources/suppressions.py
mailtrap/api/resources/templates.py
mailtrap/models/__init__.py
mailtrap/models/accounts.py
mailtrap/models/attachments.py
mailtrap/models/billing.py
mailtrap/models/common.py
mailtrap/models/contacts.py
mailtrap/models/inboxes.py
mailtrap/models/messages.py
mailtrap/models/permissions.py
mailtrap/models/projects.py
mailtrap/models/suppressions.py
mailtrap/models/templates.py
mailtrap/models/mail/__init__.py
mailtrap/models/mail/address.py
mailtrap/models/mail/attachment.py
mailtrap/models/mail/batch_mail.py
mailtrap/models/mail/mail.py
mailtrap-2.3.0.dist-info/licenses/LICENSE.txt
mailtrap-2.3.0.dist-info/METADATA
mailtrap-2.3.0.dist-info/WHEEL
mailtrap-2.3.0.dist-info/top_level.txt
mailtrap-2.3.0.dist-info/RECORD
