Metadata-Version: 2.4
Name: mailtrap
Version: 2.3.0
Summary: Official mailtrap.io API client
Author-email: Railsware Products Studio LLC <support@mailtrap.io>
License: The MIT License (MIT)
Project-URL: Homepage, https://mailtrap.io/
Project-URL: Documentation, https://github.com/railsware/mailtrap-python
Project-URL: Repository, https://github.com/railsware/mailtrap-python.git
Project-URL: API documentation, https://api-docs.mailtrap.io/
Classifier: License :: OSI Approved :: MIT License
Classifier: Operating System :: OS Independent
Classifier: Topic :: Software Development :: Libraries :: Application Frameworks
Classifier: Programming Language :: Python :: 3
Classifier: Programming Language :: Python :: 3.9
Classifier: Programming Language :: Python :: 3.10
Classifier: Programming Language :: Python :: 3.11
Classifier: Programming Language :: Python :: 3.12
Classifier: Programming Language :: Python :: 3.13
Requires-Python: >=3.9
License-File: LICENSE.txt
Requires-Dist: requests>=2.26.0
Requires-Dist: pydantic>=2.11.7
Dynamic: license-file
